{
  "name": "月德",
  "enabled": true,
  "priority": 41,
  "category": "吉神",
  "rarity": "R",
  "effect": "性情溫和，處事圓融",
  "modernMeaning": "為人和善，人緣好，少災少難",
  "buff": "月德護身",
  "debuff": null,
  "rules": [
    {
      "anchor": "monthBranch",
      "rule_ref": "傳統對照-月支取月德位（三合局）",
      "matchTarget": "anyStem",
      "table": {
        "寅": ["丙"],
        "午": ["丙"],
        "戌": ["丙"],
        "申": ["壬"],
        "子": ["壬"],
        "辰": ["壬"],
        "亥": ["甲"],
        "卯": ["甲"],
        "未": ["甲"],
        "巳": ["庚"],
        "酉": ["庚"],
        "丑": ["庚"]
      },
      "notes": "寅午戌→丙、申子辰→壬、亥卯未→甲、巳酉丑→庚"
    }
  ]
}
